passphraseme/__init__.py
passphraseme/__main__.py
passphraseme/wordlists/eff_large_wordlist.txt
passphraseme/wordlists/eff_short_wordlist_1.txt
passphraseme/wordlists/eff_short_wordlist_2_0.txt
passphraseme/wordlists/gameofthrones-2018.txt
passphraseme/wordlists/harrypotter-2018.txt
passphraseme/wordlists/startrek-2018.txt
passphraseme/wordlists/starwars-2018.txt
passphraseme-0.1.7.dist-info/LICENSE.md
passphraseme-0.1.7.dist-info/METADATA
passphraseme-0.1.7.dist-info/WHEEL
passphraseme-0.1.7.dist-info/entry_points.txt
passphraseme-0.1.7.dist-info/top_level.txt
passphraseme-0.1.7.dist-info/RECORD
