Metadata-Version: 2.1
Name: passphraseme
Version: 0.1.7
Summary: A quick and simple cryptographically secure script to generate high entropy passphrases using the Electronic Frontier Foundation's wordlists
Home-page: https://github.com/micahflee/passphraseme
Author: Micah Lee
Author-email: micah@micahflee.com
License: GPLv3+
Classifier: Programming Language :: Python
Classifier: Topic :: Security :: Cryptography
Classifier: Topic :: Software Development :: Libraries :: Python Modules
Classifier: License :: OSI Approved :: GNU General Public License v3 or later (GPLv3+)
Classifier: Intended Audience :: End Users/Desktop
Classifier: Intended Audience :: Developers
Classifier: Operating System :: OS Independent
Classifier: Intended Audience :: System Administrators
License-File: LICENSE.md
